dotnetfile/__init__.py
dotnetfile/constants.py
dotnetfile/dotnetfile.py
dotnetfile/logger.py
dotnetfile/metadata_rows.py
dotnetfile/parser.py
dotnetfile/structures.py
dotnetfile/util.py
dotnetfile-0.2.9.dist-info/licenses/LICENSE
tools/__init__.py
tools/dotnetfile_disassemble.py
tools/dotnetfile_dump.py
dotnetfile-0.2.9.dist-info/METADATA
dotnetfile-0.2.9.dist-info/WHEEL
dotnetfile-0.2.9.dist-info/entry_points.txt
dotnetfile-0.2.9.dist-info/top_level.txt
dotnetfile-0.2.9.dist-info/RECORD
